setup.py
printc/__init__.py
printc/print.py
printc.egg-info/PKG-INFO
printc.egg-info/SOURCES.txt
printc.egg-info/dependency_links.txt
printc.egg-info/not-zip-safe
printc.egg-info/top_level.txt