Metadata-Version: 1.0
Name: printc
Version: 0.2
Summary: Perform color output
Home-page: UNKNOWN
Author: xuyiwen
Author-email: daqvha@163.com
License: UNKNOWN
Platform: UNKNOWN
